dcrpm/__init__.py
dcrpm/__version__.py
dcrpm/dcrpm.py
dcrpm/forensic_logger.py
dcrpm/main.py
dcrpm/pidutil.py
dcrpm/rpmutil.py
dcrpm/util.py
dcrpm/yum.py
dcrpm-0.6.3.dist-info/LICENSE
dcrpm-0.6.3.dist-info/METADATA
dcrpm-0.6.3.dist-info/WHEEL
dcrpm-0.6.3.dist-info/entry_points.txt
dcrpm-0.6.3.dist-info/top_level.txt
dcrpm-0.6.3.dist-info/RECORD
