Metadata-Version: 2.1
Name: dcrpm
Version: 0.6.3
Summary: A tool to detect and correct common issues around RPM database corruption.
Home-page: https://github.com/facebookincubator/dcrpm
Author: Sean Karlage
Author-email: skarlage@fb.com
License: GPLv2
Keywords: bdb,db_recover,db4,dcrpm,dnf,rpm,yum
Platform: UNKNOWN
Classifier: Operating System :: POSIX :: Linux
Classifier: Intended Audience :: Developers
Classifier: Intended Audience :: System Administrators
Classifier: Programming Language :: Python :: 2.7
Classifier: Programming Language :: Python :: 3.6
Classifier: Programming Language :: Python :: 3.7
Classifier: Programming Language :: Python :: 3.8
Classifier: Programming Language :: Python :: 3.9
Classifier: Programming Language :: Python :: 3.10
Classifier: Development Status :: 3 - Alpha
Classifier: Topic :: Utilities
Classifier: License :: OSI Approved :: GNU General Public License v2 (GPLv2)
License-File: LICENSE
Requires-Dist: psutil
Provides-Extra: release
Requires-Dist: twine ; extra == 'release'
Requires-Dist: wheel ; extra == 'release'
